dicpp-0.1.7.data/data/LICENSE
dicpp-0.1.7.data/data/README.md
dicpp.libs/libgomp-f7e03b3e.so.1.0.0
dicpp/logger.py
dicpp/__init__.py
dicpp/stitch.py
dicpp/fit_data.py
dicpp/version.py
dicpp/fit_data_core.cpython-36m-x86_64-linux-gnu.so
dicpp/interpolate.py
dicpp-0.1.7.dist-info/LICENSE
dicpp-0.1.7.dist-info/METADATA
dicpp-0.1.7.dist-info/top_level.txt
dicpp-0.1.7.dist-info/RECORD
dicpp-0.1.7.dist-info/WHEEL
