Metadata-Version: 2.1
Name: dicpp
Version: 0.1.7
Summary: Digital Image Correlation (DIC) Post Processing 
Home-page: https://github.com/saullocastro/dicpp
Author: Saullo G. P. Castro
Author-email: S.G.P.Castro@tudelft.nl
License: 2-Clause BSD
Keywords: shell; cylindrical; conical; measurement; imperfection; digital image correlation
Platform: UNKNOWN
Classifier: Development Status :: 4 - Beta
Classifier: Intended Audience :: Education
Classifier: Intended Audience :: Science/Research
Classifier: Intended Audience :: Developers
Classifier: Topic :: Scientific/Engineering :: Mathematics
Classifier: Topic :: Education
Classifier: License :: OSI Approved :: BSD License
Classifier: Programming Language :: Python :: 3.7
Classifier: Programming Language :: Python :: 3.8
Classifier: Programming Language :: Python :: 3.9
Classifier: Operating System :: Microsoft :: Windows
Classifier: Operating System :: Unix
License-File: LICENSE
Requires-Dist: numpy
Requires-Dist: scipy
